kedro_pandera/__init__.py
kedro_pandera/framework/__init__.py
kedro_pandera/framework/cli/__init__.py
kedro_pandera/framework/cli/cli.py
kedro_pandera/framework/config/__init__.py
kedro_pandera/framework/config/resolvers.py
kedro_pandera/framework/hooks/__init__.py
kedro_pandera/framework/hooks/pandera_hook.py
kedro_pandera-0.2.3.dist-info/LICENSE
kedro_pandera-0.2.3.dist-info/METADATA
kedro_pandera-0.2.3.dist-info/WHEEL
kedro_pandera-0.2.3.dist-info/entry_points.txt
kedro_pandera-0.2.3.dist-info/top_level.txt
kedro_pandera-0.2.3.dist-info/RECORD
