Metadata-Version: 2.1
Name: kedro-pandera
Version: 0.2.3
Summary: A kedro plugin to use pandera in your kedro projects
Home-page: https://github.com/Galileo-Galilei/kedro-pandera
Author: Yolan Honoré-Rougé
License: Apache Software License (Apache 2.0)
Classifier: Development Status :: 4 - Beta
Classifier: Programming Language :: Python :: 3.8
Classifier: Programming Language :: Python :: 3.9
Classifier: Programming Language :: Python :: 3.10
Classifier: Programming Language :: Python :: 3.11
Classifier: Framework :: Kedro
Classifier: Environment :: Plugins
Classifier: Intended Audience :: Developers
Classifier: Operating System :: Microsoft :: Windows
Classifier: Operating System :: MacOS
Classifier: Operating System :: POSIX :: Linux
Requires-Python: >=3.8, <3.12
License-File: LICENSE
Requires-Dist: pandera[io] >=0.15
Requires-Dist: kedro <0.20,>=0.19.0
Provides-Extra: dev
Requires-Dist: pre-commit <4.0.0,>=2.0.0 ; extra == 'dev'
Requires-Dist: jupyter <2.0.0,>=1.0.0 ; extra == 'dev'
Provides-Extra: doc
Requires-Dist: sphinx <7.5.0,>=4.5.0 ; extra == 'doc'
Requires-Dist: sphinxawesome-theme ; extra == 'doc'
Requires-Dist: sphinx-docsearch ; extra == 'doc'
Requires-Dist: sphinx-markdown-tables ~=0.0.15 ; extra == 'doc'
Requires-Dist: sphinx-click <7.0,>=3.1 ; extra == 'doc'
Requires-Dist: sphinx-copybutton ~=0.5.0 ; extra == 'doc'
Requires-Dist: sphinx-design ; extra == 'doc'
Requires-Dist: myst-parser <3.1.0,>=0.17.2 ; extra == 'doc'
Provides-Extra: test
Requires-Dist: ruff <0.6.0,>=0.5.0 ; extra == 'test'
Requires-Dist: pyspark <4.0,>=2.2 ; extra == 'test'
Requires-Dist: pytest <9.0.0,>=7.0.0 ; extra == 'test'
Requires-Dist: pytest-cov <6.0.0,>=4.0.0 ; extra == 'test'
Requires-Dist: pytest-mock ; extra == 'test'
Requires-Dist: pre-commit <4.0.0,>=2.0.0 ; extra == 'test'
Requires-Dist: cookiecutter ; extra == 'test'
Requires-Dist: kedro-datasets ; extra == 'test'
